export_metabase.py
import_metabase.py
sync_metabase.py
lib/__init__.py
lib/client.py
lib/config.py
lib/constants.py
lib/errors.py
lib/models_core.py
lib/py.typed
lib/version.py
lib/handlers/__init__.py
lib/handlers/base.py
lib/handlers/card.py
lib/handlers/collection.py
lib/handlers/dashboard.py
lib/handlers/permissions.py
lib/models/__init__.py
lib/remapping/__init__.py
lib/remapping/id_mapper.py
lib/remapping/query_remapper.py
lib/services/__init__.py
lib/services/export_service.py
lib/services/import_service.py
lib/utils/__init__.py
lib/utils/file_io.py
lib/utils/logging.py
lib/utils/payload.py
lib/utils/sanitization.py
metabase_migration_toolkit-1.1.0.dist-info/licenses/LICENSE
metabase_migration_toolkit-1.1.0.dist-info/METADATA
metabase_migration_toolkit-1.1.0.dist-info/WHEEL
metabase_migration_toolkit-1.1.0.dist-info/entry_points.txt
metabase_migration_toolkit-1.1.0.dist-info/top_level.txt
metabase_migration_toolkit-1.1.0.dist-info/RECORD
