Metadata-Version: 2.4
Name: metabase-migration-toolkit
Version: 1.1.0
Summary: Export and import Metabase content (collections, questions, dashboards) between instances
Author: Metabase Migration Toolkit Contributors
License: MIT
Project-URL: Homepage, https://github.com/Finverity/metabase-migration-toolkit
Project-URL: Documentation, https://github.com/Finverity/metabase-migration-toolkit#readme
Project-URL: Repository, https://github.com/Finverity/metabase-migration-toolkit
Project-URL: Bug Tracker, https://github.com/Finverity/metabase-migration-toolkit/issues
Project-URL: Changelog, https://github.com/Finverity/metabase-migration-toolkit/blob/main/CHANGELOG.md
Keywords: metabase,migration,export,import,backup,analytics,business-intelligence,bi-tools
Classifier: Development Status :: 4 - Beta
Classifier: Intended Audience :: Developers
Classifier: Intended Audience :: System Administrators
Classifier: License :: OSI Approved :: MIT License
Classifier: Operating System :: OS Independent
Classifier: Programming Language :: Python :: 3
Classifier: Programming Language :: Python :: 3.10
Classifier: Programming Language :: Python :: 3.11
Classifier: Programming Language :: Python :: 3.12
Classifier: Topic :: Database
Classifier: Topic :: System :: Archiving :: Backup
Classifier: Topic :: Utilities
Classifier: Typing :: Typed
Requires-Python: >=3.10
License-File: LICENSE
Requires-Dist: requests>=2.28.0
Requires-Dist: tqdm>=4.64.0
Requires-Dist: tenacity>=8.1.0
Requires-Dist: python-dotenv>=0.20.0
Requires-Dist: pydantic>=2.0.0
Provides-Extra: dev
Requires-Dist: pytest>=7.0.0; extra == "dev"
Requires-Dist: pytest-cov>=4.0.0; extra == "dev"
Requires-Dist: pytest-mock>=3.10.0; extra == "dev"
Requires-Dist: black>=23.0.0; extra == "dev"
Requires-Dist: ruff>=0.1.0; extra == "dev"
Requires-Dist: mypy>=1.0.0; extra == "dev"
Requires-Dist: types-requests>=2.28.0; extra == "dev"
Requires-Dist: pre-commit>=3.0.0; extra == "dev"
Requires-Dist: isort>=5.0.0; extra == "dev"
Provides-Extra: docs
Requires-Dist: sphinx>=5.0.0; extra == "docs"
Requires-Dist: sphinx-rtd-theme>=1.0.0; extra == "docs"
Requires-Dist: sphinx-autodoc-typehints>=1.19.0; extra == "docs"
Dynamic: license-file
